mathtools/__init__.py
mathtools/mathtools.py
mathtools_uio-0.0.2.dist-info/LICENSE
mathtools_uio-0.0.2.dist-info/METADATA
mathtools_uio-0.0.2.dist-info/WHEEL
mathtools_uio-0.0.2.dist-info/top_level.txt
mathtools_uio-0.0.2.dist-info/RECORD
