Metadata-Version: 2.1
Name: mathtools-uio
Version: 0.0.2
Summary: A package to help me do math
Home-page: https://github.com/thelexxirose/mathtools
Author: Cory Alexander Balaton
Author-email: cory.balaton@gmail.com
License: UNKNOWN
Project-URL: Bug Tracker, https://github.com/thelexxirose/mathtools/issues
Platform: UNKNOWN
Classifier: Programming Language :: Python :: 3
Classifier: License :: OSI Approved :: MIT License
Classifier: Operating System :: OS Independent
Requires-Python: >=3.6
License-File: LICENSE
